CHANGELOG.md
pyyaml_object/__init__.py
pyyaml_object/config.py
pyyaml_object/utils.py
pyaml_object-2.0.1.post0.dist-info/LICENSE
pyaml_object-2.0.1.post0.dist-info/METADATA
pyaml_object-2.0.1.post0.dist-info/WHEEL
pyaml_object-2.0.1.post0.dist-info/RECORD
