Metadata-Version: 2.1
Name: pyaml-object
Version: 2.0.1.post0
Summary: Read your YAML files easily
Home-page: https://github.com/EM51641/PyYAMEL-object/tree/main
License: MIT
Author: Elyes
Author-email: elyesmahjoubi@gmail.com
Maintainer: Elyes
Maintainer-email: elyesmahjoubi@gmail.com
Requires-Python: >=3.8,<4.0
Classifier: License :: OSI Approved :: MIT License
Classifier: Operating System :: OS Independent
Classifier: Programming Language :: Python :: 3
Classifier: Programming Language :: Python :: 3.8
Classifier: Programming Language :: Python :: 3.9
Classifier: Programming Language :: Python :: 3.10
Classifier: Programming Language :: Python :: 3.11
Classifier: Topic :: Software Development :: Build Tools
Classifier: Topic :: Software Development :: Libraries :: Python Modules
Requires-Dist: pyyaml (>=6.0.1,<7.0.0)
Project-URL: Repository, https://github.com/EM51641/PyYAMEL-object/tree/main
